pretix_zugferd/__init__.py
pretix_zugferd/apps.py
pretix_zugferd/invoice.py
pretix_zugferd/signals.py
pretix_zugferd/urls.py
pretix_zugferd/views.py
pretix_zugferd/locale/django.pot
pretix_zugferd/locale/de/LC_MESSAGES/django.mo
pretix_zugferd/locale/de/LC_MESSAGES/django.po
pretix_zugferd/locale/de_Informal/.gitkeep
pretix_zugferd/locale/de_Informal/LC_MESSAGES/django.mo
pretix_zugferd/locale/de_Informal/LC_MESSAGES/django.po
pretix_zugferd/migrations/0001_initial.py
pretix_zugferd/migrations/__init__.py
pretix_zugferd/static/pretix_zugferd/.gitkeep
pretix_zugferd/templates/pretix_zugferd/.gitkeep
pretix_zugferd/templates/pretix_zugferd/settings.html
pretix_zugferd-2.6.2.dist-info/licenses/LICENSE
pretix_zugferd-2.6.2.dist-info/METADATA
pretix_zugferd-2.6.2.dist-info/WHEEL
pretix_zugferd-2.6.2.dist-info/entry_points.txt
pretix_zugferd-2.6.2.dist-info/top_level.txt
pretix_zugferd-2.6.2.dist-info/RECORD
