Metadata-Version: 2.4
Name: pretix-zugferd
Version: 2.6.2
Summary: Invoice renderer that annotates pretix invoices with ZUGFeRD data
Author-email: pretix team <support@pretix.eu>
Maintainer-email: pretix team <support@pretix.eu>
License: Copyright 2018 Raphael Michel
Project-URL: homepage, https://github.com/pretixeu/pretix-zugferd
Keywords: pretix
Requires-Python: >=3.9
License-File: LICENSE
Requires-Dist: drafthorse==2025.2.0
Dynamic: license-file
